sky/__init__.py
sky/authentication.py
sky/check.py
sky/cli.py
sky/cloud_stores.py
sky/core.py
sky/dag.py
sky/exceptions.py
sky/execution.py
sky/global_user_state.py
sky/optimizer.py
sky/resources.py
sky/sky_logging.py
sky/skypilot_config.py
sky/status_lib.py
sky/task.py
sky/adaptors/__init__.py
sky/adaptors/aws.py
sky/adaptors/azure.py
sky/adaptors/cloudflare.py
sky/adaptors/docker.py
sky/adaptors/gcp.py
sky/adaptors/ibm.py
sky/adaptors/oci.py
sky/backends/__init__.py
sky/backends/backend.py
sky/backends/backend_utils.py
sky/backends/cloud_vm_ray_backend.py
sky/backends/docker_utils.py
sky/backends/local_docker_backend.py
sky/backends/onprem_utils.py
sky/backends/wheel_utils.py
sky/backends/monkey_patches/monkey_patch_ray_up.py
sky/benchmark/__init__.py
sky/benchmark/benchmark_state.py
sky/benchmark/benchmark_utils.py
sky/clouds/__init__.py
sky/clouds/aws.py
sky/clouds/azure.py
sky/clouds/cloud.py
sky/clouds/gcp.py
sky/clouds/ibm.py
sky/clouds/lambda_cloud.py
sky/clouds/local.py
sky/clouds/oci.py
sky/clouds/scp.py
sky/clouds/service_catalog/__init__.py
sky/clouds/service_catalog/aws_catalog.py
sky/clouds/service_catalog/azure_catalog.py
sky/clouds/service_catalog/common.py
sky/clouds/service_catalog/config.py
sky/clouds/service_catalog/constants.py
sky/clouds/service_catalog/gcp_catalog.py
sky/clouds/service_catalog/ibm_catalog.py
sky/clouds/service_catalog/lambda_catalog.py
sky/clouds/service_catalog/oci_catalog.py
sky/clouds/service_catalog/scp_catalog.py
sky/clouds/service_catalog/data_fetchers/__init__.py
sky/clouds/service_catalog/data_fetchers/fetch_aws.py
sky/clouds/service_catalog/data_fetchers/fetch_azure.py
sky/clouds/service_catalog/data_fetchers/fetch_gcp.py
sky/clouds/service_catalog/data_fetchers/fetch_lambda_cloud.py
sky/data/__init__.py
sky/data/data_transfer.py
sky/data/data_utils.py
sky/data/mounting_utils.py
sky/data/storage.py
sky/data/storage_utils.py
sky/provision/__init__.py
sky/provision/aws/__init__.py
sky/provision/aws/instance.py
opilot-1.0.0.dev0.dist-info/LICENSE
opilot-1.0.0.dev0.dist-info/METADATA
opilot-1.0.0.dev0.dist-info/WHEEL
opilot-1.0.0.dev0.dist-info/entry_points.txt
opilot-1.0.0.dev0.dist-info/top_level.txt
opilot-1.0.0.dev0.dist-info/RECORD
