Metadata-Version: 2.1
Name: opilot
Version: 1.0.0.dev0
Summary: OpenPilot: An intercloud broker for the clouds
Author: OpenPilot Team
License: Apache 2.0
Project-URL: Homepage, https://github.com/openlmai/openpilot
Project-URL: Issues, https://github.com/openlmai/openpilot/issues
Project-URL: Discussion, https://github.com/openlmai/openpilot/discussions
Project-URL: Documentation, https://openpilot.readthedocs.io/en/latest/
Classifier: Programming Language :: Python :: 3.7
Classifier: Programming Language :: Python :: 3.8
Classifier: Programming Language :: Python :: 3.9
Classifier: Programming Language :: Python :: 3.10
Classifier: License :: OSI Approved :: Apache Software License
Classifier: Operating System :: OS Independent
Classifier: Topic :: Software Development :: Libraries :: Python Modules
Classifier: Topic :: System :: Distributed Computing
License-File: LICENSE
Requires-Dist: wheel
Requires-Dist: click (<=8.0.4,>=7.0)
Requires-Dist: colorama (<0.4.5)
Requires-Dist: cryptography
Requires-Dist: jinja2 (>=3.0)
Requires-Dist: jsonschema
Requires-Dist: networkx
Requires-Dist: oauth2client
Requires-Dist: pandas
Requires-Dist: pendulum
Requires-Dist: PrettyTable (>=2.0.0)
Requires-Dist: python-dotenv
Requires-Dist: ray[default] (<=2.4.0,>=2.2.0)
Requires-Dist: rich
Requires-Dist: tabulate
Requires-Dist: filelock (>=3.6.0)
Requires-Dist: packaging
Requires-Dist: protobuf (!=3.19.5,>=3.15.3)
Requires-Dist: psutil
Requires-Dist: pulp
Requires-Dist: pydantic (<2.0)
Requires-Dist: pyyaml (<=5.3.1,>3.13)
Requires-Dist: awscli
Requires-Dist: boto3
Requires-Dist: pycryptodome (==3.12.0)
Requires-Dist: grpcio (!=1.48.0,<=1.51.3,>=1.32.0) ; python_version < "3.10" and sys_platform != "darwin"
Requires-Dist: grpcio (!=1.48.0,<=1.49.1,>=1.32.0) ; python_version < "3.10" and sys_platform == "darwin"
Requires-Dist: typing-extensions ; python_version < "3.8"
Requires-Dist: grpcio (!=1.48.0,<=1.51.3,>=1.42.0) ; python_version >= "3.10" and sys_platform != "darwin"
Requires-Dist: grpcio (!=1.48.0,<=1.49.1,>=1.42.0) ; python_version >= "3.10" and sys_platform == "darwin"
Provides-Extra: all
Requires-Dist: awscli ; extra == 'all'
Requires-Dist: boto3 ; extra == 'all'
Requires-Dist: pycryptodome (==3.12.0) ; extra == 'all'
Requires-Dist: azure-cli (>=2.31.0) ; extra == 'all'
Requires-Dist: azure-core ; extra == 'all'
Requires-Dist: azure-identity (>=1.13.0) ; extra == 'all'
Requires-Dist: azure-mgmt-network ; extra == 'all'
Requires-Dist: google-api-python-client ; extra == 'all'
Requires-Dist: google-cloud-storage ; extra == 'all'
Requires-Dist: ibm-cloud-sdk-core ; extra == 'all'
Requires-Dist: ibm-vpc ; extra == 'all'
Requires-Dist: ibm-platform-services ; extra == 'all'
Requires-Dist: docker ; extra == 'all'
Requires-Dist: oci ; extra == 'all'
Provides-Extra: aws
Requires-Dist: awscli ; extra == 'aws'
Requires-Dist: boto3 ; extra == 'aws'
Requires-Dist: pycryptodome (==3.12.0) ; extra == 'aws'
Provides-Extra: azure
Requires-Dist: azure-cli (>=2.31.0) ; extra == 'azure'
Requires-Dist: azure-core ; extra == 'azure'
Requires-Dist: azure-identity (>=1.13.0) ; extra == 'azure'
Requires-Dist: azure-mgmt-network ; extra == 'azure'
Provides-Extra: cloudflare
Requires-Dist: awscli ; extra == 'cloudflare'
Requires-Dist: boto3 ; extra == 'cloudflare'
Requires-Dist: pycryptodome (==3.12.0) ; extra == 'cloudflare'
Provides-Extra: docker
Requires-Dist: docker ; extra == 'docker'
Provides-Extra: gcp
Requires-Dist: google-api-python-client ; extra == 'gcp'
Requires-Dist: google-cloud-storage ; extra == 'gcp'
Provides-Extra: ibm
Requires-Dist: ibm-cloud-sdk-core ; extra == 'ibm'
Requires-Dist: ibm-vpc ; extra == 'ibm'
Requires-Dist: ibm-platform-services ; extra == 'ibm'
Provides-Extra: lambda
Provides-Extra: oci
Requires-Dist: oci ; extra == 'oci'
Provides-Extra: scp
